modules/inference/build/lib/nefertem_inference/__init__.py
modules/inference/build/lib/nefertem_inference/metadata/__init__.py
modules/inference/build/lib/nefertem_inference/metadata/report.py
modules/inference/build/lib/nefertem_inference/plugins/builder.py
modules/inference/build/lib/nefertem_inference/plugins/plugin.py
modules/inference/build/lib/nefertem_inference/plugins/utils.py
modules/inference/build/lib/nefertem_inference/run/__init__.py
modules/inference/build/lib/nefertem_inference/run/run.py
modules/inference/nefertem_inference/__init__.py
modules/inference/nefertem_inference/metadata/__init__.py
modules/inference/nefertem_inference/metadata/report.py
modules/inference/nefertem_inference/plugins/builder.py
modules/inference/nefertem_inference/plugins/plugin.py
modules/inference/nefertem_inference/plugins/utils.py
modules/inference/nefertem_inference/run/__init__.py
modules/inference/nefertem_inference/run/run.py
modules/metric/build/lib/nefertem_metric/__init__.py
modules/metric/build/lib/nefertem_metric/metadata/__init__.py
modules/metric/build/lib/nefertem_metric/metadata/report.py
modules/metric/build/lib/nefertem_metric/plugins/__init__.py
modules/metric/build/lib/nefertem_metric/plugins/builder.py
modules/metric/build/lib/nefertem_metric/plugins/metric.py
modules/metric/build/lib/nefertem_metric/plugins/plugin.py
modules/metric/build/lib/nefertem_metric/run/__init__.py
modules/metric/build/lib/nefertem_metric/run/run.py
modules/metric/nefertem_metric/__init__.py
modules/metric/nefertem_metric/metadata/__init__.py
modules/metric/nefertem_metric/metadata/report.py
modules/metric/nefertem_metric/plugins/__init__.py
modules/metric/nefertem_metric/plugins/builder.py
modules/metric/nefertem_metric/plugins/metric.py
modules/metric/nefertem_metric/plugins/plugin.py
modules/metric/nefertem_metric/run/__init__.py
modules/metric/nefertem_metric/run/run.py
modules/profiling/build/lib/nefertem_profiling/__init__.py
nefertem-2.0.6.dist-info/LICENSE.txt
nefertem-2.0.6.dist-info/METADATA
nefertem-2.0.6.dist-info/WHEEL
nefertem-2.0.6.dist-info/top_level.txt
nefertem-2.0.6.dist-info/RECORD
