Metadata-Version: 2.1
Name: nefertem
Version: 2.0.6
Summary: Python data validation library
Author-email: Fondazione Bruno Kessler <dslab@fbk.eu>, Matteo Martini <mmartini@fbk.eu>
License: Apache License
Project-URL: Homepage, https://github.com/scc-digitalhub/nefertem
Keywords: data,validation,quality
Classifier: License :: OSI Approved :: Apache Software License
Classifier: Programming Language :: Python :: 3.9
Classifier: Programming Language :: Python :: 3.10
Classifier: Programming Language :: Python :: 3.11
Requires-Python: >=3.9
License-File: LICENSE.txt
Requires-Dist: nefertem-core ~=2.0
Provides-Extra: all
Requires-Dist: nefertem-inference ~=2.0 ; extra == 'all'
Requires-Dist: nefertem-profiling ~=2.0 ; extra == 'all'
Requires-Dist: nefertem-validation ~=2.0 ; extra == 'all'
Provides-Extra: dev
Requires-Dist: black ; extra == 'dev'
Requires-Dist: pytest ; extra == 'dev'
Requires-Dist: moto ; extra == 'dev'
Requires-Dist: bumpver ; extra == 'dev'
Provides-Extra: docs
Requires-Dist: Sphinx ==5.3.0 ; extra == 'docs'
Requires-Dist: pydata-sphinx-theme ==0.13.3 ; extra == 'docs'
Requires-Dist: autodoc-pydantic ==1.8.0 ; extra == 'docs'
Requires-Dist: numpydoc ==1.5.0 ; extra == 'docs'
